pcalib/__init__.py
pcalib/py/__init__.py
pcalib/py/algorithms.py
pcalib/py/libpca_lib.dylib
pcalib/py/matrix.py
pcalib-0.1.4.dist-info/LICENSE
pcalib-0.1.4.dist-info/METADATA
pcalib-0.1.4.dist-info/WHEEL
pcalib-0.1.4.dist-info/top_level.txt
pcalib-0.1.4.dist-info/RECORD
